Logger/Logger.py
Logger/__init__.py
loggerpyth-1.3.dist-info/METADATA
loggerpyth-1.3.dist-info/WHEEL
loggerpyth-1.3.dist-info/top_level.txt
loggerpyth-1.3.dist-info/RECORD
