Metadata-Version: 2.1
Name: loggerpyth
Version: 1.3
Summary: Logging made simple and beautiful
Home-page: UNKNOWN
Author: Bilodev (Antonio Bilotta)
Author-email: bilotta.antonio.biz@gmail.com
License: UNKNOWN
Keywords: python,Log,Logging,Debug,TUI,Terminal
Platform: UNKNOWN
Classifier: Development Status :: 5 - Production/Stable
Classifier: Intended Audience :: Developers
Classifier: Programming Language :: Python :: 3
Classifier: Operating System :: Unix
Classifier: Operating System :: MacOS :: MacOS X
Classifier: Operating System :: Microsoft :: Windows
Requires-Dist: print-color
